setup.cfg
setup.py
teem/__init__.py
teem/client.py
teem/server.py
teem/storages.py
teem/text_operation.py
teem_py.egg-info/PKG-INFO
teem_py.egg-info/SOURCES.txt
teem_py.egg-info/dependency_links.txt
teem_py.egg-info/top_level.txt