Metadata-Version: 1.1
Name: teem-py
Version: 0.1.0
Summary: Collaborative editing with OT in Python Edit
Home-page: https://github.com/jeffschenck/teem-py
Author: Jeff Schenck
Author-email: jmschenck@gmail.com
License: MIT
Download-URL: https://github.com/jeffschenck/teem-py
Platform: UNKNOWN
Classifier: Development Status :: 4 - Beta
Classifier: Environment :: Web Environment
Classifier: Intended Audience :: Developers
Classifier: Programming Language :: Python :: 2
Classifier: Programming Language :: Python :: 2.6
Classifier: Programming Language :: Python :: 2.7
Classifier: Programming Language :: Python :: 3
Classifier: Programming Language :: Python :: 3.3
Classifier: Programming Language :: Python :: 3.4
Classifier: Programming Language :: Python :: 3.5
Classifier: Programming Language :: Python :: 3.6
Classifier: Programming Language :: Python :: Implementation :: CPython
Classifier: Programming Language :: Python :: Implementation :: PyPy
Classifier: License :: OSI Approved :: MIT License
